README.txt
connect
setup.py
cli/__init__.py
cli/configuration.py
cli/commands/__init__.py
cli/commands/vagrant.py
cli/framework/__init__.py
cli/framework/authenticate.py
cli/framework/git_core.py
gosolid_connect_cli.egg-info/PKG-INFO
gosolid_connect_cli.egg-info/SOURCES.txt
gosolid_connect_cli.egg-info/dependency_links.txt
gosolid_connect_cli.egg-info/requires.txt
gosolid_connect_cli.egg-info/top_level.txt