Metadata-Version: 1.1
Name: gosolid-connect-cli
Version: 1.1.0
Summary: CLI for interfacing with GoSolid projects
Home-page: http://gosolid.net/
Author: Andrew Venglar
Author-email: andrew@gosolid.net
License: GPLv3
Platform: UNKNOWN
Classifier: Environment :: Console
Classifier: Intended Audience :: Developers
Classifier: Intended Audience :: Information Technology
Classifier: Intended Audience :: System Administrators
Classifier: Natural Language :: English
Classifier: Operating System :: POSIX
Classifier: Programming Language :: Python :: 2.7
Classifier: Topic :: Utilities
